itwinai/__init__.py
itwinai/cli.py
itwinai/components.py
itwinai/constants.py
itwinai/distributed.py
itwinai/loggers.py
itwinai/parser.py
itwinai/pipeline.py
itwinai/serialization.py
itwinai/type.py
itwinai/utils.py
itwinai/plugins/__init__.py
itwinai/scalability_report/data.py
itwinai/scalability_report/plot.py
itwinai/scalability_report/reports.py
itwinai/scalability_report/utils.py
itwinai/slurm/configuration.py
itwinai/slurm/constants.py
itwinai/slurm/script_builder.py
itwinai/slurm/utils.py
itwinai/tensorflow/__init__.py
itwinai/tensorflow/distributed.py
itwinai/tensorflow/trainer.py
itwinai/tensorflow/utils.py
itwinai/tensorflow/data/__init__.py
itwinai/tensorflow/models/__init__.py
itwinai/tensorflow/models/mnist.py
itwinai/tests/__init__.py
itwinai/tests/distributed.py
itwinai/tests/dummy_components.py
itwinai/tests/exceptions.py
itwinai/tests/sanity_check.py
itwinai/torch/__init__.py
itwinai/torch/config.py
itwinai/torch/distributed.py
itwinai/torch/gan.py
itwinai/torch/inference.py
itwinai/torch/loggers.py
itwinai/torch/mlflow.py
itwinai/torch/reproducibility.py
itwinai/torch/trainer.py
itwinai/torch/tuning.py
itwinai/torch/type.py
itwinai/torch/utils.py
itwinai/torch/data/__init__.py
itwinai/torch/models/__init__.py
itwinai/torch/models/mnist.py
itwinai/torch/monitoring/backend.py
itwinai/torch/monitoring/monitoring.py
itwinai/torch/profiling/profiler.py
itwinai/torch/profiling/py_spy_aggregation.py
itwinai-0.4.1.dist-info/licenses/LICENSE
itwinai-0.4.1.dist-info/METADATA
itwinai-0.4.1.dist-info/WHEEL
itwinai-0.4.1.dist-info/entry_points.txt
itwinai-0.4.1.dist-info/top_level.txt
itwinai-0.4.1.dist-info/RECORD
