Metadata-Version: 2.4
Name: itwinai
Version: 0.4.1
Summary: AI and ML workflows module for scientific digital twins.
Maintainer-email: Matteo Bunino <matteo.bunino@cern.ch>, Jarl Sondre Sæther <jarl.sondre.saether@cern.ch>, Anna Lappe <anna.elisa.lappe@cern.ch>, Linus Eickhoff <linus.maximilian.eickhoff@cern.ch>
License:                                  Apache License
Project-URL: Homepage, https://www.intertwin.eu/
Project-URL: Documentation, https://itwinai.readthedocs.io/
Project-URL: Repository, https://github.com/interTwin-eu/itwinai
Keywords: ml,ai,hpc
Classifier: Development Status :: 4 - Beta
Classifier: Programming Language :: Python
Requires-Python: >=3.10
License-File: LICENSE
Requires-Dist: rich>=13.5.3
Requires-Dist: typer>=0.9.0
Requires-Dist: numpy<2.0.0
Requires-Dist: wandb>=0.18.7
Requires-Dist: mlflow>=2.17.2
Requires-Dist: wheel>=0.45.0
Requires-Dist: seaborn>=0.13.2
Requires-Dist: py-cpuinfo>=9.0.0
Requires-Dist: packaging>=24.2
Requires-Dist: pydantic>=2.10.2
Requires-Dist: pyyaml>=6.0.2
Requires-Dist: omegaconf>=2.3.0
Requires-Dist: jsonargparse[signatures]>=4.34.0
Requires-Dist: matplotlib>=3.9.2
Requires-Dist: pip>=24.3.1
Requires-Dist: ray[default,train,tune]>=2.43.0
Requires-Dist: tensorboard>=2.16.2
Requires-Dist: hydra-core>=1.3.2
Requires-Dist: pynvml>=12.0.0
Requires-Dist: py-spy>=0.4.0
Requires-Dist: tabulate>=0.9.0
Requires-Dist: click==8.1.8
Requires-Dist: validators>=0.35.0
Provides-Extra: amd
Requires-Dist: amdsmi>=6.4.0; extra == "amd"
Provides-Extra: torch
Requires-Dist: torch==2.6.*; extra == "torch"
Requires-Dist: lightning>=2; extra == "torch"
Requires-Dist: torchmetrics>=1.6.0; extra == "torch"
Requires-Dist: torchvision>=0.16.2; extra == "torch"
Requires-Dist: torchaudio>=2.4.0; extra == "torch"
Requires-Dist: torch-fidelity>=0.3.0; extra == "torch"
Requires-Dist: torchrun-jsc>=0.0.18; extra == "torch"
Provides-Extra: tf
Requires-Dist: tensorflow==2.16.*; extra == "tf"
Requires-Dist: tf_keras==2.16.*; extra == "tf"
Provides-Extra: tf-cuda
Requires-Dist: tensorflow[and-cuda]==2.16.*; extra == "tf-cuda"
Requires-Dist: tf_keras==2.16.*; extra == "tf-cuda"
Provides-Extra: dev
Requires-Dist: pytest>=7.4.2; extra == "dev"
Requires-Dist: pytest-mock>=3.11.1; extra == "dev"
Requires-Dist: pytest-cov>=4.1.0; extra == "dev"
Requires-Dist: ipykernel>=6.29.5; extra == "dev"
Requires-Dist: ipython>=8.30.0; extra == "dev"
Requires-Dist: ruff>=0.8.3; extra == "dev"
Requires-Dist: psutil>=6.1.0; extra == "dev"
Requires-Dist: pytest-xdist>=3.6.1; extra == "dev"
Provides-Extra: docs
Requires-Dist: sphinx-rtd-theme>=2.0.0; extra == "docs"
Requires-Dist: nbsphinx>=0.9.4; extra == "docs"
Requires-Dist: myst-parser>=2.0.0; extra == "docs"
Requires-Dist: IPython>=8.30.0; extra == "docs"
Requires-Dist: sphinx-tabs>=3.4.7; extra == "docs"
Requires-Dist: sphinx-copybutton>=0.5.2; extra == "docs"
Requires-Dist: sphinx-design>=0.6.1; extra == "docs"
Provides-Extra: hpo
Requires-Dist: bayesian-optimization>=2.0.0; extra == "hpo"
Requires-Dist: hyperopt>=0.2.0; extra == "hpo"
Requires-Dist: ConfigSpace>=1.2.0; extra == "hpo"
Requires-Dist: hpbandster>=0.7.0; extra == "hpo"
Requires-Dist: gpy>=1.13.2; extra == "hpo"
Dynamic: license-file
